location_history_total/__init__.py
location_history_total/__main__.py
location_history_total/totaler.py
location_history_total-0.1.2.dist-info/LICENSE
location_history_total-0.1.2.dist-info/WHEEL
location_history_total-0.1.2.dist-info/METADATA
location_history_total-0.1.2.dist-info/RECORD
